alu.v
module alu( reset, tclk, instruction, ldAcc, useAlu, dbusSelect, acc, latch, c, z, d_bus );

input reset, tclk; //reset ,clock
input [7:0] instruction; //instruction register
input ldAcc, useAlu, dbusSelect; //control signal
output [7:0] acc, latch; //accumulator,latch
reg [7:0] acc, latch;
output c,z; //carry_flag ,zero_flag
reg c, z;
inout [7:0] d_bus; //data bus

always @(posedge tclk or posedge reset) begin
    if (reset) begin 
        acc<=8'b0; latch<=8'b0; c<=1'b0; z<=1'b0; 
    end
    else begin
    if(useAlu) begin //EXEC_Aの時,算術命令とSTを行う
        casex(instruction[7:5])
            3'b000: begin//ADD 
                {c,latch}<=acc + d_bus;
                z<=((acc + d_bus)==8'b0);
                end 
            3'b001: begin//SUB
                {c,latch}<=acc - d_bus; 
                z<=((acc - d_bus)==8'b0);
                end 
            3'b010: begin//NAND 
                {c,latch}<=~(acc & d_bus); 
                z<=((~(acc & d_bus))==8'b0);
                end
            3'b011: begin //SHIFT
                if(instruction[4:0]==5'h1f)begin //RIGHT SHIFT
                {c,latch}<=acc >> 1; 
                z<=((acc >>1 )==8'b0);
                end
                else begin {c,latch}<=acc << 1; //LEFT SHIFT
                z<=((acc <<1 )==8'b0); 
                end
                end
            3'b101: latch<=acc; //ST
        endcase
    end
    if(ldAcc) acc<=d_bus; //EXEC_Aの時LD行う
    end
end

assign d_bus= (dbusSelect)? latch: 8'bz; //EXEC_Bの時latchの値をd_busへ流すor流さない(ハイインピーダンス) 

parameter FETCH = 2'b00, DECODE = 2'b01, EXEC_A = 2'b10, EXEC_B = 2'b11;

endmodule

alu_test.v
`timescale 1ns/1ns
module alu_test;

//input signal (clock)
reg tclk = 1;
always #(STEP/2) tclk<=!tclk;

//input signal
reg reset;
reg [7:0] instruction;
reg ldAcc, useAlu, dbusSelect;
reg [7:0] in_d_bus; //d_busの中身を変えるための変数


//output siganl
wire c,z;
wire [7:0] acc,latch;
wire [7:0] d_bus;

//inout信号の入力をそのまま出力に流すか(Execute cycle Aの時にd_busの中身を変えるため)
reg inout_flag = 1;

//双方向信号対応用
assign d_bus = (inout_flag)? in_d_bus: 8'bz;

parameter STEP = 100;

alu alu( reset, tclk, instruction, ldAcc, useAlu, dbusSelect, acc, latch, c, z, d_bus );

    initial begin

        reset=1'b0; instruction=8'b01100000; ldAcc = 1'b0; useAlu = 1'b0; dbusSelect = 1'b0; 
        in_d_bus = 8'bz;

        //正常動作の確認
            //Fetch cycle　ALU付近は何もしない
            #STEP instruction =8'b01101000;
            #STEP

            //reset
            #STEP reset = 1'b1;
            #STEP reset = 1'b0;

            //Execute cycle A
                //LD命令
                #STEP in_d_bus = 8'b10011110; ldAcc = 1'b1;
                //ADD命令
                #STEP ldAcc = 1'b0; useAlu = 1'b1; in_d_bus = 8'b01100001; instruction = 8'b000xxxxx;
                //SUB命令
                #STEP instruction = 8'b001xxxxx; in_d_bus = 8'b10011110; 
                //NAND命令
                #STEP instruction = 8'b010xxxxx; in_d_bus = 8'b10101010; 
                //SHIFT命令
                #STEP instruction = 8'b01100000; //LEFT SHIFT
                #STEP instruction = 8'b01111111; //RIGHT SHIFT
                //ST命令
                #STEP in_d_bus = 8'b11111111; ldAcc = 1'b1;
                #STEP instruction = 8'b101xxxxx;  ldAcc = 1'b0;

            #STEP useAlu = 1'b0; 
            
            //Execute cycle B
                #STEP in_d_bus = 8'b10101010; inout_flag = 1'b0;
                #STEP dbusSelect = 1'b1;
                #STEP dbusSelect = 1'b0;
        
        //異常入力の時の動作
            //reset
            #STEP reset = 1'bx;
            #STEP reset = 1'bz;
            #STEP reset = 1'b1;
            #STEP reset = 1'b0;

            //Execute cycle A
                #STEP useAlu = 1'b1; inout_flag = 1'b1;
                #STEP instruction = 8'bxxxxxxxx;
                #STEP instruction = 8'bzzzzzzzz;
                #STEP useAlu = 1'bx;
                #STEP instruction = 8'b001xxxxx;
                #STEP useAlu = 1'bz;
                #STEP instruction = 8'b001xxxxx;

            //Execute cycle B
                #STEP dbusSelect = 1'bx; inout_flag = 1'b0; useAlu = 1'b0;
                #STEP dbusSelect = 1'bz;

        #STEP $finish;
    end

    initial begin
        $dumpfile("alu_out.vcd");
        $dumpvars(0, alu_test);
    end

endmodule

alu_out.vcd
$date
	Wed Feb 10 12:24:17 2021
$end
$version
	Icarus Verilog
$end
$timescale
	1ns
$end
$scope module alu_test $end
$var wire 8 ! d_bus [7:0] $end
$var wire 1 " z $end
$var wire 8 # latch [7:0] $end
$var wire 1 $ c $end
$var wire 8 % acc [7:0] $end
$var reg 1 & dbusSelect $end
$var reg 8 ' in_d_bus [7:0] $end
$var reg 1 ( inout_flag $end
$var reg 8 ) instruction [7:0] $end
$var reg 1 * ldAcc $end
$var reg 1 + reset $end
$var reg 1 , tclk $end
$var reg 1 - useAlu $end
$scope module alu $end
$var wire 8 . d_bus [7:0] $end
$var wire 1 & dbusSelect $end
$var wire 8 / instruction [7:0] $end
$var wire 1 * ldAcc $end
$var wire 1 + reset $end
$var wire 1 , tclk $end
$var wire 1 - useAlu $end
$var reg 8 0 acc [7:0] $end
$var reg 1 $ c $end
$var reg 8 1 latch [7:0] $end
$var reg 1 " z $end
$upscope $end
$upscope $end
$enddefinitions $end
#0
$dumpvars
bx 1
bx 0
b1100000 /
bz .
0-
1,
0+
0*
b1100000 )
1(
bz '
0&
bx %
x$
bx #
x"
bz !
$end
#50
0,
#100
1,
b1101000 )
b1101000 /
#150
0,
#200
1,
#250
0,
#300
0"
0$
b0 #
b0 1
b0 %
b0 0
1,
1+
#350
0,
#400
1,
0+
#450
0,
#500
b10011110 %
b10011110 0
1,
b10011110 !
b10011110 .
1*
b10011110 '
#550
0,
#600
b11111111 #
b11111111 1
1,
b1100001 !
b1100001 .
b0xxxxx )
b0xxxxx /
b1100001 '
1-
0*
#650
0,
#700
1"
b0 #
b0 1
1,
b10011110 !
b10011110 .
b10011110 '
b1xxxxx )
b1xxxxx /
#750
0,
#800
0"
1$
b1110101 #
b1110101 1
1,
b10101010 !
b10101010 .
b10101010 '
b10xxxxx )
b10xxxxx /
#850
0,
#900
b111100 #
b111100 1
1,
b1100000 )
b1100000 /
#950
0,
#1000
0$
b1001111 #
b1001111 1
1,
b1111111 )
b1111111 /
#1050
0,
#1100
b11111111 %
b11111111 0
1,
b11111111 !
b11111111 .
1*
b11111111 '
#1150
0,
#1200
b11111111 #
b11111111 1
1,
0*
b101xxxxx )
b101xxxxx /
#1250
0,
#1300
1,
0-
#1350
0,
#1400
1,
bz !
bz .
0(
b10101010 '
#1450
0,
#1500
1,
b11111111 !
b11111111 .
1&
#1550
0,
#1600
1,
bz !
bz .
0&
#1650
0,
#1700
1,
x+
#1750
0,
#1800
1,
z+
#1850
0,
#1900
b0 #
b0 1
b0 %
b0 0
1,
1+
#1950
0,
#2000
1,
0+
#2050
0,
#2100
1,
b10101010 !
b10101010 .
1(
1-
#2150
0,
#2200
b10101010 #
b10101010 1
1,
bx )
bx /
#2250
0,
#2300
1,
bz )
bz /
#2350
0,
#2400
1,
x-
#2450
0,
#2500
1,
b1xxxxx )
b1xxxxx /
#2550
0,
#2600
1,
z-
#2650
0,
#2700
1,
#2750
0,
#2800
1,
bx !
bx .
0-
0(
x&
#2850
0,
#2900
1,
z&
