mem.v
module mem(tclk, a_bus, inp, oup, instruction, dbusSelect, d_bus, view_mem);

input tclk; //clock
input [4:0] a_bus; //adress bas
input [7:0] inp; //input
input [7:0] instruction; //instruction register
input dbusSelect; //control signal
output [7:0] oup; // output
inout [7:0] d_bus; //data bas
reg [7:0] mem[0:31];
reg [7:0] oup;

//------memの内容を見るための変数 結合テストの時には消す-----
output [7:0] view_mem; 
assign view_mem =mem[a_bus];
//----------------------------------------

function [7:0] memout; // memory read
    input [4:0] a_bus;
    case(a_bus)
        //ROM 0~4番地
        0:memout =8'b10011110; //inputをACCにLD
        1:memout =8'b10111111; //ACCをoutputにST
        2:memout =8'b01000100; //ACCと5'b00100(=4)番地の内容とのnand後にACCに代入
        3:memout =8'b11100000; //JPNZ
        4:memout =8'b00000000; //ACCと5'b00000のADD後にACCに代入

        //RAM 5~29番地

        //input=30 output=31番地
        30:memout =inp;
        default: memout =mem[a_bus];
    endcase
endfunction

always @(posedge tclk) begin
    if(instruction[7:5] == 3'b100 )begin
        if (a_bus==31) oup<=d_bus;  
        else mem[a_bus] <=d_bus;
    end
end

assign d_bus = (~(dbusSelect))? memout(a_bus): 8'bz;//EXEC_Bの時memoutの値をd_busへ流すor流さない(ハイインピーダンス) 

endmodule

mem_test.v
`timescale 1ns/1ns
module mem_test;
//input signal (clock)
reg tclk = 1;
always #(STEP/2) tclk<=!tclk;

//input signal
reg [4:0] a_bus; 
reg [7:0] inp; 
reg [7:0] instruction; 
reg dbusSelect; 
reg [7:0] in_d_bus;

//output siganl
wire [7:0] oup;
wire [7:0] d_bus;
wire [7:0] view_mem;
//inout信号の入力をそのまま出力に流すか(d_busの中身を変えるため)
reg inout_flag ;

//双方向信号対応用
assign d_bus = (inout_flag)? in_d_bus: 8'bz;

parameter STEP = 100;

mem mem( tclk, a_bus, inp, oup, instruction, dbusSelect, d_bus, view_mem );

    initial begin

        instruction=8'b010xxxxx; inp = 8'h0; dbusSelect = 1'b1; 
        in_d_bus = 8'bz; inout_flag = 1'b0;

        //正常動作の確認
            //0~4番地までを読みだしてd_busに流す
            #STEP dbusSelect = 1'b0; a_bus = 4'd0;
            #STEP a_bus = 4'd1;
            #STEP a_bus = 4'd2;
            #STEP a_bus = 4'd3;
            #STEP a_bus = 4'd4;
            //30番地(input)をd_busに流す
            #STEP a_bus = 30; inp=8'b11111111;
            //LD命令の時
                //d_busの内容をoutputするとき
                #STEP instruction = 8'b10000000; in_d_bus = 8'b01010101; a_bus = 31; inout_flag = 1'b1; dbusSelect = 1'b1;
                //d_busの内容をRAMに書き込むとき
                #STEP a_bus = 5; 
        
        //異常入力の時の動作
            //制御信号がおかしい時
            #STEP dbusSelect = 1'bx; inout_flag = 1'b0; instruction=8'b010xxxxx;
            #STEP dbusSelect = 1'bz;

            //番地がおかしい時にどうd_busにながれるか
            #STEP dbusSelect = 1'b0; a_bus = 4'b000x; inout_flag = 1'b0; dbusSelect = 1'b0;
            #STEP a_bus = 4'b000z;


        #STEP $finish;
    end

    initial begin
        $dumpfile("mem_out.vcd");
        $dumpvars(0, mem_test);
    end


endmodule

mem_out.vcd
$date
	Wed Feb 10 17:28:20 2021
$end
$version
	Icarus Verilog
$end
$timescale
	1ns
$end
$scope module mem_test $end
$var wire 8 ! d_bus [7:0] $end
$var wire 8 " view_mem [7:0] $end
$var wire 8 # oup [7:0] $end
$var reg 5 $ a_bus [4:0] $end
$var reg 1 % dbusSelect $end
$var reg 8 & in_d_bus [7:0] $end
$var reg 1 ' inout_flag $end
$var reg 8 ( inp [7:0] $end
$var reg 8 ) instruction [7:0] $end
$var reg 1 * tclk $end
$scope module mem $end
$var wire 5 + a_bus [4:0] $end
$var wire 8 , d_bus [7:0] $end
$var wire 1 % dbusSelect $end
$var wire 8 - inp [7:0] $end
$var wire 8 . instruction [7:0] $end
$var wire 1 * tclk $end
$var wire 8 / view_mem [7:0] $end
$var reg 8 0 oup [7:0] $end
$scope function memout $end
$var reg 5 1 a_bus [4:0] $end
$upscope $end
$upscope $end
$upscope $end
$enddefinitions $end
#0
$dumpvars
bx 1
bx 0
bx /
b10xxxxx .
b0 -
bz ,
bx +
1*
b10xxxxx )
b0 (
0'
bz &
1%
bx $
bx #
bx "
bz !
$end
#50
0*
#100
1*
b10011110 !
b10011110 ,
b0 1
b0 $
b0 +
0%
#150
0*
#200
1*
b10111111 !
b10111111 ,
b1 1
b1 $
b1 +
#250
0*
#300
1*
b1000100 !
b1000100 ,
b10 1
b10 $
b10 +
#350
0*
#400
1*
b11100000 !
b11100000 ,
b11 1
b11 $
b11 +
#450
0*
#500
1*
b0 !
b0 ,
b100 1
b100 $
b100 +
#550
0*
#600
1*
b11111111 !
b11111111 ,
b11110 1
b11111111 (
b11111111 -
b11110 $
b11110 +
#650
0*
#700
b1010101 #
b1010101 0
1*
b1010101 !
b1010101 ,
b11111 1
1%
1'
b11111 $
b11111 +
b1010101 &
b10000000 )
b10000000 .
#750
0*
#800
b1010101 "
b1010101 /
1*
b101 1
b101 $
b101 +
#850
0*
#900
1*
bx !
bx ,
b10xxxxx )
b10xxxxx .
0'
x%
#950
0*
#1000
1*
z%
#1050
0*
#1100
1*
b0x 1
bx "
bx /
b0x $
b0x +
0%
#1150
0*
#1200
1*
b0z 1
b0z $
b0z +
